CHANGES.md
IDEAS.md
LICENSE.txt
MANIFEST.in
README.md
README.rst
manage.py
notes.md
requirements.txt
runtests.py
setup.py
start_local_popit_api.bash
test_settings.py
popit/__init__.py
popit/admin.py
popit/fields.py
popit/models.py
popit/views.py
popit/management/__init__.py
popit/management/commands/__init__.py
popit/management/commands/popit_retrieve_all.py
popit/migrations/0001_initial.py
popit/migrations/0002_auto__add_apiinstance.py
popit/migrations/0003_auto__add_person.py
popit/migrations/0004_auto__add_field_person_image__add_field_person_summary.py
popit/migrations/0005_auto__add_field_person_popit_id.py
popit/migrations/0006_update_popit_id_from_url.py
popit/migrations/__init__.py
popit/tests/__init__.py
popit/tests/instance_helpers.py
popit/tests/test_popit_instance.py
popit/tests/test_popit_person.py
popit/tests/fixtures/__init__.py
popit/tests/fixtures/default.js
popit/tests/fixtures/rename_joe_bloggs.js
popit/tests/fixtures/too_many_people.js
popit_django.egg-info/PKG-INFO
popit_django.egg-info/SOURCES.txt
popit_django.egg-info/dependency_links.txt
popit_django.egg-info/requires.txt
popit_django.egg-info/top_level.txt