Metadata-Version: 1.1
Name: popit-django
Version: 0.0.3
Summary: Use PopIt stored data in your Django app
Home-page: https://github.com/mysociety/popit-django
Author: mySociety
Author-email: modules@mysociety.org
License: GNU Affero General Public License v3
Platform: UNKNOWN
Classifier: Development Status :: 3 - Alpha
Classifier: Environment :: Web Environment
Classifier: Framework :: Django
Classifier: Intended Audience :: Developers
Classifier: License :: OSI Approved :: GNU Affero General Public License v3
Classifier: Operating System :: OS Independent
Classifier: Programming Language :: Python
